AUTHORS.rst
CONTRIBUTING.rst
HISTORY.rst
LICENSE
MANIFEST.in
README.rst
setup.py
django_periodicals.egg-info/PKG-INFO
django_periodicals.egg-info/SOURCES.txt
django_periodicals.egg-info/dependency_links.txt
django_periodicals.egg-info/not-zip-safe
django_periodicals.egg-info/requires.txt
django_periodicals.egg-info/top_level.txt
periodicals/__init__.py
periodicals/admin.py
periodicals/models.py
periodicals/search_indexes.py
periodicals/sitemaps.py
periodicals/urls.py
periodicals/views.py
periodicals/static/js/periodicals.js
periodicals/templates/periodicals/add_link_form.html
periodicals/templates/periodicals/article_detail.html
periodicals/templates/periodicals/article_tag_detail.html
periodicals/templates/periodicals/author_detail.html
periodicals/templates/periodicals/author_list.html
periodicals/templates/periodicals/base.html
periodicals/templates/periodicals/base_periodical.html
periodicals/templates/periodicals/base_periodicals.html
periodicals/templates/periodicals/issue_detail.html
periodicals/templates/periodicals/issue_year.html
periodicals/templates/periodicals/link_add.html
periodicals/templates/periodicals/link_success.html
periodicals/templates/periodicals/links.html
periodicals/templates/periodicals/periodical_detail.html
periodicals/templates/periodicals/periodical_list.html
periodicals/templates/periodicals/read_online.html
periodicals/templates/periodicals/search.html
periodicals/templates/periodicals/series_detail.html
periodicals/templates/periodicals/series_list.html
periodicals/templates/periodicals/tag_cloud.html
periodicals/templates/periodicals/tags.html
periodicals/templates/search/search.html
periodicals/templatetags/__init__.py
periodicals/templatetags/periodicals_tags.py