Metadata-Version: 1.0
Name: django-periodicals
Version: 0.8.0
Summary: Django app to create periodical/magazine websites"
Home-page: https://github.com/saschwarz/django-periodicals
Author: Steve Schwarz
Author-email: steve@agilitynerd.com
License: BSD
Keywords: django-periodicals
Platform: UNKNOWN
Classifier: Development Status :: 3 - Alpha
Classifier: Framework :: Django
Classifier: Intended Audience :: Developers
Classifier: License :: OSI Approved :: BSD License
Classifier: Natural Language :: English
Classifier: Programming Language :: Python :: 2
Classifier: Programming Language :: Python :: 2.6
Classifier: Programming Language :: Python :: 2.7
